code2image/__about__.py
code2image/__init__.py
code2image/__main__.py
code2image/cli.py
code2image/cls.py
code2image/util.py
tests/__init__.py
tests/test_cls.py
code2image-0.0.3.dist-info/LICENSE
code2image-0.0.3.dist-info/METADATA
code2image-0.0.3.dist-info/WHEEL
code2image-0.0.3.dist-info/entry_points.txt
code2image-0.0.3.dist-info/top_level.txt
code2image-0.0.3.dist-info/RECORD
