Metadata-Version: 2.1
Name: code2image
Version: 0.0.3
Summary: Create code snippet with pygments and pillow
Home-page: https://github.com/axju/code2image
Author: Axel Juraske
Author-email: axel.juraske@short-report.de
License: MIT
Keywords: pillow image pygments code snippets
Platform: UNKNOWN
Classifier: Intended Audience :: Developers
Classifier: Operating System :: OS Independent
Classifier: Programming Language :: Python
Classifier: Programming Language :: Python :: 3.5
Classifier: Programming Language :: Python :: 3.6
Classifier: Programming Language :: Python :: 3.7
Requires-Dist: pygments
Requires-Dist: pillow
